sphinx_panel_screenshot/__init__.py
sphinx_panel_screenshot/_version.py
sphinx_panel_screenshot/plot_directive.py
sphinx_panel_screenshot/utils.py
sphinx_panel_screenshot-0.2.0.dist-info/LICENSE
sphinx_panel_screenshot-0.2.0.dist-info/METADATA
sphinx_panel_screenshot-0.2.0.dist-info/WHEEL
sphinx_panel_screenshot-0.2.0.dist-info/top_level.txt
sphinx_panel_screenshot-0.2.0.dist-info/RECORD
