Metadata-Version: 2.1
Name: sphinx-panel-screenshot
Version: 0.2.0
Summary: A directive to include panel's screenshots into a Sphinx document
Home-page: https://github.com/Davide-sd/sphinx_panel_screenshot
Author: Davide Sandona
Author-email: sandona.davide@gmail.com
License: MIT License
Keywords: panel sphinx screenshot
Classifier: Development Status :: 5 - Production/Stable
Classifier: License :: OSI Approved :: MIT License
Classifier: Programming Language :: Python :: 3.10
Classifier: Topic :: Documentation
Classifier: Topic :: Documentation :: Sphinx
License-File: LICENSE
Requires-Dist: panel
Requires-Dist: selenium
Requires-Dist: webdriver-manager
Requires-Dist: sphinx
Requires-Dist: pillow
Provides-Extra: dev
Requires-Dist: pytest ; extra == 'dev'
Requires-Dist: hvplot ; extra == 'dev'
